ctnx/__init__.py
ctnx/constants.py
ctnx/legacy.py
ctnx/misc.py
ctnx/number.py
ctnx/sort.py
ctnx/syllable.py
ctnx/validation.py
chiecthuyenngoaixa-0.2.1.dist-info/LICENSE
chiecthuyenngoaixa-0.2.1.dist-info/METADATA
chiecthuyenngoaixa-0.2.1.dist-info/WHEEL
chiecthuyenngoaixa-0.2.1.dist-info/RECORD
